CHANGELOG.txt
LICENCE.txt
MANIFEST.in
README.txt
setup.py
fasteda/__init__.py
fasteda.egg-info/PKG-INFO
fasteda.egg-info/SOURCES.txt
fasteda.egg-info/dependency_links.txt
fasteda.egg-info/requires.txt
fasteda.egg-info/top_level.txt